pyalic/__init__.py
pyalic/exceptions.py
pyalic/fingerprint.py
pyalic/lm.py
pyalic/response.py
pyalic/wrappers.py
pyalic/asyncio/__init__.py
pyalic/asyncio/lm.py
pyalic/asyncio/wrappers.py
pyalic-1.0.1.dist-info/LICENSE
pyalic-1.0.1.dist-info/METADATA
pyalic-1.0.1.dist-info/WHEEL
pyalic-1.0.1.dist-info/top_level.txt
pyalic-1.0.1.dist-info/RECORD
