Metadata-Version: 2.1
Name: pyalic
Version: 1.0.1
Summary: Licensing system module which allows you to manage access to your products with ease
Home-page: https://github.com/Yarosvet/Pyalic
Author: Yarosvet
Classifier: Programming Language :: Python :: 3.8
Classifier: License :: OSI Approved :: GNU Lesser General Public License v2 (LGPLv2)
Classifier: Operating System :: OS Independent
Classifier: Development Status :: 5 - Production/Stable
Classifier: Topic :: Software Development :: Libraries :: Python Modules
License-File: LICENSE
Requires-Dist: httpx
